tf_rbdl/__init__.py
tf_rbdl/dynamics.py
tf_rbdl/kinematics.py
tf_rbdl/liegroup.py
tf_rbdl/utils.py
tf_rbdl-2.0.3.dist-info/LICENSE
tf_rbdl-2.0.3.dist-info/METADATA
tf_rbdl-2.0.3.dist-info/WHEEL
tf_rbdl-2.0.3.dist-info/top_level.txt
tf_rbdl-2.0.3.dist-info/RECORD
