Metadata-Version: 2.1
Name: tf-rbdl
Version: 2.0.3
Summary: Rigid Body Dynamics Library using Tensorflow.
Home-page: https://github.com/junhyeokahn/tf_rbdl
Author: Junhyeok Ahn
Author-email: junhyeokahn91@gmail.com
License: MIT
Platform: UNKNOWN
Classifier: License :: OSI Approved :: MIT License
Classifier: Programming Language :: Python
Classifier: Programming Language :: Python :: 3
Classifier: Programming Language :: Python :: 3.6
Classifier: Programming Language :: Python :: Implementation :: CPython
Classifier: Programming Language :: Python :: Implementation :: PyPy
Requires-Python: >=3.6.0
Requires-Dist: numpy (>=1.16.0)
Requires-Dist: setuptools (>=41.0.0)
Provides-Extra: examples
Requires-Dist: pybullet ; extra == 'examples'
Requires-Dist: gym ; extra == 'examples'
Requires-Dist: tqdm ; extra == 'examples'
Provides-Extra: tf
Requires-Dist: tensorflow (>=2.0.0) ; extra == 'tf'
Provides-Extra: tf_gpu
Requires-Dist: tensorflow-gpu (>=2.0.0) ; extra == 'tf_gpu'
